.gitignore
LICENSE.txt
README.rst
setup.py
r00imena/__init__.py
r00imena/firstname_female_eng.txt
r00imena/firstname_female_rus.txt
r00imena/firstname_female_ukr.txt
r00imena/firstname_male_eng.txt
r00imena/firstname_male_rus.txt
r00imena/firstname_male_ukr.txt
r00imena/lastname_female_eng.txt
r00imena/lastname_female_rus.txt
r00imena/lastname_female_ukr.txt
r00imena/lastname_male_eng.txt
r00imena/lastname_male_rus.txt
r00imena/lastname_male_ukr.txt
r00imena/otch_female_rus.txt
r00imena/otch_female_ukr.txt
r00imena/otch_male_rus.txt
r00imena/otch_male_ukr.txt
r00imena.egg-info/PKG-INFO
r00imena.egg-info/SOURCES.txt
r00imena.egg-info/dependency_links.txt
r00imena.egg-info/top_level.txt