Metadata-Version: 1.0
Name: r00imena
Version: 0.2
Summary: UNKNOWN
Home-page: UNKNOWN
Author: Andrey Ivanov
Author-email: r00ft1h@gmail.com
License: MIT
Platform: UNKNOWN
